asvs_compliance_tools-2.2.0.dist-info/licenses/LICENSE
tools/__init__.py
tools/cli.py
tools/compliance_gate.py
tools/drift_detector.py
tools/export_requirements.py
tools/generate_report.py
tools/iac_scanner.py
tools/init_project.py
tools/verification_suite.py
asvs_compliance_tools-2.2.0.dist-info/METADATA
asvs_compliance_tools-2.2.0.dist-info/WHEEL
asvs_compliance_tools-2.2.0.dist-info/entry_points.txt
asvs_compliance_tools-2.2.0.dist-info/top_level.txt
asvs_compliance_tools-2.2.0.dist-info/RECORD
