Metadata-Version: 2.4
Name: asvs-compliance-tools
Version: 2.2.0
Summary: ASVS Compliance Starter Kit - CLI tools for security requirements management
Author: ASVS Compliance Team
License: MIT
Keywords: asvs,security,compliance,owasp
Classifier: Development Status :: 4 - Beta
Classifier: Intended Audience :: Developers
Classifier: License :: OSI Approved :: MIT License
Classifier: Programming Language :: Python :: 3
Classifier: Programming Language :: Python :: 3.9
Classifier: Programming Language :: Python :: 3.10
Classifier: Programming Language :: Python :: 3.11
Classifier: Programming Language :: Python :: 3.12
Classifier: Programming Language :: Python :: 3.13
Classifier: Topic :: Security
Requires-Python: >=3.9
License-File: LICENSE
Provides-Extra: verification
Requires-Dist: requests>=2.28.0; extra == "verification"
Provides-Extra: evidence
Requires-Dist: PyYAML>=6.0; extra == "evidence"
Provides-Extra: dev
Requires-Dist: pytest>=7.0.0; extra == "dev"
Requires-Dist: pytest-cov>=4.0.0; extra == "dev"
Dynamic: license-file
